counter/counterwithtestbench.v
module counter(clk,reset,up,down,salida);
input clk,reset,up,down;
output wire [6:0] salida;
reg [6:0] number;
reg [2:0] current_state,next_state;
parameter S0 = 3'b000;
parameter S1 = 3'b001;
parameter S2 = 3'b010;
parameter S3 = 3'b011;
parameter S4 = 3'b100;
parameter S5 = 3'b101;
parameter S6 = 3'b110;

always @(posedge clk, posedge reset)begin
    if(reset) begin
        current_state <= S0;
    end
    else
        current_state <= next_state;
end

always @(current_state,up, down)
begin
    case(current_state)
        S0: begin
            if(up)begin
                next_state = S1;
            end
            else if(down) begin
                next_state = S3;
            end
        end
        S1: begin
            if(~up)begin
                next_state = S2;
            end
            else if(down) begin
                next_state = S3;
            end
        end
        S3: begin
            if(~down) begin
                next_state = S4;
            end
            else if(up) begin
                next_state = S1;
            end
        end
        S2: begin
            if(up) begin
                next_state = S1;
            end
            else if(down)begin
                next_state = S3;
            end
            else 
                next_state = S5;
        end
       S4: begin
            if(down) begin
                next_state = S3;
            end
            else if(up) begin
                next_state = S1;
            end
            else
                next_state = S6;
        end
        S5:begin
            if(up) begin
                next_state = S1;
            end
            else if(down) begin
                next_state = S3;
            end
            else
                next_state = S2;
        end
        S6:
            if(up)begin
                next_state = S1;
            end
            else if(down)begin
                next_state = S3;
            end
            else 
                next_state = S4;

        default: next_state = S0;
    endcase
end


always @(posedge clk)
begin
    case(current_state)
        S0:begin
            number <= 0;
        end
        S1: begin
            if(~up)begin
                number <= (number+1 > 100 ? 0: number + 1);
            end
        end
        S2: begin
            if(~up) begin
                number <= (number+1 > 100 ? 0: number + 1);
            end
        end
        S3: begin
            if(~down) begin
                number <= (number-1 > 100 ? 100:number -1);
            end
        end
        S4: begin
            if(~down) begin
                number <= (number-1 > 100 ? 100:number -1);
            end
        end
        S5:begin
            if(~up) begin
                number <= (number+1 > 100 ? 0: number + 1);
            end
        end
        S6:begin
            if(~down) begin
                number <= (number- 1> 100 ? 100:number -1);
            end
        end
    endcase
end

assign salida = number;

endmodule


module test_bench;
reg up,down,clk,reset;
wire [6:0] number;
counter instancia(clk,reset,up,down,number);
initial begin
    clk = 0; reset = 1;up = 0; down = 0; 
    #1 clk = 1; reset = 1; up = 0; down = 0;
    #1 clk = 0; reset = 0; up = 0; down = 0;
    #1 clk = 1; reset = 0; up = 0; down = 0;
    #1 clk = 0; reset = 0; up = 0; down = 0;
    #1 clk = 1; reset = 0; up = 1; down = 0;
    #1 clk = 0; reset = 0; up = 0; down = 0;
    #1 clk = 1; reset = 0; up = 0; down = 0;
    #1 clk = 0; reset = 0; up = 0; down = 0;
    #1 clk = 1; reset = 0; up = 0; down = 0;
    #1 clk = 0; reset = 0; up = 0; down = 0;
    #1 clk = 1; reset = 0; up = 0; down = 0;
    #1 clk = 0; reset = 0; up = 0; down = 0;
    #1 clk = 1; reset = 0; up = 0; down = 0;
    #1 clk = 0; reset = 0; up = 0; down = 0;
    #1 clk = 1; reset = 0; up = 0; down = 0;
    #1 clk = 0; reset = 0; up = 0; down = 0;
    #1 clk = 1; reset = 0; up = 0; down = 0;
    #1 clk = 0; reset = 0; up = 0; down = 0;
    #1 clk = 1; reset = 0; up = 0; down = 0;
    #1 clk = 0; reset = 0; up = 0; down = 0;
    #1 clk = 1; reset = 0; up = 0; down = 0;
    #1 clk = 0; reset = 0; up = 0; down = 0;
    #1 clk = 1; reset = 0; up = 0; down = 0;
    #1 clk = 0; reset = 0; up = 0; down = 0;
    #1 clk = 1; reset = 0; up = 0; down = 0;
    #1 clk = 0; reset = 0; up = 0; down = 0;
    #1 clk = 1; reset = 0; up = 0; down = 0;
    #1 clk = 0; reset = 0; up = 0; down = 0;
    #1 clk = 1; reset = 0; up = 0; down = 0;
    #1 clk = 0; reset = 0; up = 0; down = 0;
    #1 clk = 1; reset = 0; up = 0; down = 0;
    #1 clk = 0; reset = 0; up = 0; down = 0;
    #1 clk = 1; reset = 0; up = 0; down = 0;
    #1 clk = 0; reset = 0; up = 0; down = 0;
    #1 clk = 1; reset = 0; up = 0; down = 0;
    #1 clk = 0; reset = 0; up = 0; down = 0;
    #1 clk = 1; reset = 0; up = 0; down = 0;
    #1 clk = 0; reset = 0; up = 0; down = 0;
    #1 clk = 1; reset = 0; up = 0; down = 0;
    #1 clk = 0; reset = 0; up = 0; down = 0;
    #1 clk = 1; reset = 0; up = 0; down = 0;
    #1 clk = 0; reset = 0; up = 0; down = 0;
    #1 clk = 1; reset = 0; up = 0; down = 0;
    #1 clk = 0; reset = 0; up = 0; down = 0;
    #1 clk = 1; reset = 0; up = 0; down = 0;
    #1 clk = 0; reset = 0; up = 0; down = 0;
    #1 clk = 1; reset = 0; up = 0; down = 0;
    #1 clk = 0; reset = 0; up = 0; down = 0;
    #1 clk = 1; reset = 0; up = 0; down = 0;
    #1 clk = 0; reset = 0; up = 0; down = 0;
    #1 clk = 1; reset = 0; up = 0; down = 0;
    #1 clk = 0; reset = 0; up = 0; down = 0;
    #1 clk = 1; reset = 0; up = 0; down = 0;
    #1 clk = 0; reset = 0; up = 0; down = 0;
    #1 clk = 1; reset = 0; up = 0; down = 0;
    #1 clk = 0; reset = 0; up = 0; down = 0;
    #1 clk = 1; reset = 0; up = 0; down = 0;
    #1 clk = 0; reset = 0; up = 0; down = 0;
    #1 clk = 1; reset = 0; up = 0; down = 0;
    #1 clk = 0; reset = 0; up = 0; down = 0;
    #1 clk = 1; reset = 0; up = 0; down = 0;
    #1 clk = 0; reset = 0; up = 0; down = 0;
    #1 clk = 1; reset = 0; up = 0; down = 0;
    #1 clk = 0; reset = 0; up = 0; down = 0;
    #1 clk = 1; reset = 0; up = 0; down = 0;
    #1 clk = 0; reset = 0; up = 0; down = 0;
    #1 clk = 1; reset = 0; up = 0; down = 0;
    #1 clk = 0; reset = 0; up = 0; down = 0;
    #1 clk = 1; reset = 0; up = 0; down = 0;
    #1 clk = 0; reset = 0; up = 0; down = 0;
    #1 clk = 1; reset = 0; up = 0; down = 0;
    #1 clk = 0; reset = 0; up = 0; down = 0;
    #1 clk = 1; reset = 0; up = 0; down = 0;
    #1 clk = 0; reset = 0; up = 0; down = 0;
    #1 clk = 1; reset = 0; up = 0; down = 0;
    #1 clk = 0; reset = 0; up = 0; down = 0;
    #1 clk = 1; reset = 0; up = 0; down = 0;
    #1 clk = 0; reset = 0; up = 0; down = 0;
    #1 clk = 1; reset = 0; up = 0; down = 0;
    #1 clk = 0; reset = 0; up = 0; down = 0;
    #1 clk = 1; reset = 0; up = 0; down = 0;
    #1 clk = 0; reset = 0; up = 0; down = 0;
    #1 clk = 1; reset = 0; up = 0; down = 0;
    #1 clk = 0; reset = 0; up = 0; down = 0;
    #1 clk = 1; reset = 0; up = 0; down = 0;
    #1 clk = 0; reset = 0; up = 0; down = 0;
    #1 clk = 1; reset = 0; up = 0; down = 0;
    #1 clk = 0; reset = 0; up = 0; down = 0;
    #1 clk = 1; reset = 0; up = 0; down = 0;
    #1 clk = 0; reset = 0; up = 0; down = 0;
    #1 clk = 1; reset = 0; up = 0; down = 0;
    #1 clk = 0; reset = 0; up = 0; down = 0;
    #1 clk = 1; reset = 0; up = 0; down = 0;
    #1 clk = 0; reset = 0; up = 0; down = 0;
    #1 clk = 1; reset = 0; up = 0; down = 0;
    #1 clk = 0; reset = 0; up = 0; down = 0;
    #1 clk = 1; reset = 0; up = 0; down = 0;
    #1 clk = 0; reset = 0; up = 0; down = 0;
    #1 clk = 1; reset = 0; up = 0; down = 0;
    #1 clk = 0; reset = 0; up = 0; down = 0;
    #1 clk = 1; reset = 0; up = 0; down = 0;
    #1 clk = 0; reset = 0; up = 0; down = 0;
    #1 clk = 1; reset = 0; up = 0; down = 0;
    #1 clk = 0; reset = 0; up = 0; down = 0;
    #1 clk = 1; reset = 0; up = 0; down = 0;
    #1 clk = 0; reset = 0; up = 0; down = 0;
    #1 clk = 1; reset = 0; up = 0; down = 0;
    #1 clk = 0; reset = 0; up = 0; down = 0;
    #1 clk = 1; reset = 0; up = 0; down = 0;
    #1 clk = 0; reset = 0; up = 0; down = 0;
    #1 clk = 1; reset = 0; up = 0; down = 0;
    #1 clk = 0; reset = 0; up = 0; down = 0;
    #1 clk = 1; reset = 0; up = 0; down = 0;
    #1 clk = 0; reset = 0; up = 0; down = 0;
    #1 clk = 1; reset = 0; up = 0; down = 0;
    #1 clk = 0; reset = 0; up = 0; down = 0;
    #1 clk = 1; reset = 0; up = 0; down = 0;
    #1 clk = 0; reset = 0; up = 0; down = 0;
    #1 clk = 1; reset = 0; up = 0; down = 0;
    #1 clk = 0; reset = 0; up = 0; down = 0;
    #1 clk = 1; reset = 0; up = 0; down = 0;
    #1 clk = 0; reset = 0; up = 0; down = 0;
    #1 clk = 1; reset = 0; up = 0; down = 0;
    #1 clk = 0; reset = 0; up = 0; down = 0;
    #1 clk = 1; reset = 0; up = 0; down = 0;
    #1 clk = 0; reset = 0; up = 0; down = 0;
    #1 clk = 1; reset = 0; up = 0; down = 0;
    #1 clk = 0; reset = 0; up = 0; down = 0;
    #1 clk = 1; reset = 0; up = 0; down = 0;
    #1 clk = 0; reset = 0; up = 0; down = 0;
    #1 clk = 1; reset = 0; up = 0; down = 0;
    #1 clk = 0; reset = 0; up = 0; down = 0;
    #1 clk = 1; reset = 0; up = 0; down = 0;
    #1 clk = 0; reset = 0; up = 0; down = 0;
    #1 clk = 1; reset = 0; up = 0; down = 0;
    #1 clk = 0; reset = 0; up = 0; down = 0;
    #1 clk = 1; reset = 0; up = 0; down = 0;
    #1 clk = 0; reset = 0; up = 0; down = 0;
    #1 clk = 1; reset = 0; up = 0; down = 0;
    #1 clk = 0; reset = 0; up = 0; down = 0;
    #1 clk = 1; reset = 0; up = 0; down = 0;
    #1 clk = 0; reset = 0; up = 0; down = 0;
    #1 clk = 1; reset = 0; up = 0; down = 0;
    #1 clk = 0; reset = 0; up = 0; down = 0;
    #1 clk = 1; reset = 0; up = 0; down = 0;
    #1 clk = 0; reset = 0; up = 0; down = 0;
    #1 clk = 1; reset = 0; up = 0; down = 0;
    #1 clk = 0; reset = 0; up = 0; down = 0;
    #1 clk = 1; reset = 0; up = 0; down = 0;
    #1 clk = 0; reset = 0; up = 0; down = 0;
    #1 clk = 1; reset = 0; up = 0; down = 0;
    #1 clk = 0; reset = 0; up = 0; down = 0;
    #1 clk = 1; reset = 0; up = 0; down = 0;
    #1 clk = 0; reset = 0; up = 0; down = 0;
    #1 clk = 1; reset = 0; up = 0; down = 0;
    #1 clk = 0; reset = 0; up = 0; down = 0;
    #1 clk = 1; reset = 0; up = 0; down = 0;
    #1 clk = 0; reset = 0; up = 0; down = 0;
    #1 clk = 1; reset = 0; up = 0; down = 0;
    #1 clk = 0; reset = 0; up = 0; down = 0;
    #1 clk = 1; reset = 0; up = 0; down = 0;
    #1 clk = 0; reset = 0; up = 0; down = 0;
    #1 clk = 1; reset = 0; up = 0; down = 0;
    #1 clk = 0; reset = 0; up = 0; down = 0;
    #1 clk = 1; reset = 0; up = 0; down = 0;
    #1 clk = 0; reset = 0; up = 0; down = 0;
    #1 clk = 1; reset = 0; up = 0; down = 0;
    #1 clk = 0; reset = 0; up = 0; down = 0;
    #1 clk = 1; reset = 0; up = 0; down = 0;
    #1 clk = 0; reset = 0; up = 0; down = 0;
    #1 clk = 1; reset = 0; up = 0; down = 0;
    #1 clk = 0; reset = 0; up = 0; down = 0;
    #1 clk = 1; reset = 0; up = 0; down = 0;
    #1 clk = 0; reset = 0; up = 0; down = 0;
    #1 clk = 1; reset = 0; up = 0; down = 0;
    #1 clk = 0; reset = 0; up = 0; down = 0;
    #1 clk = 1; reset = 0; up = 0; down = 0;
    #1 clk = 0; reset = 0; up = 0; down = 0;
    #1 clk = 1; reset = 0; up = 0; down = 0;
    #1 clk = 0; reset = 0; up = 0; down = 0;
    #1 clk = 1; reset = 0; up = 0; down = 0;
    #1 clk = 0; reset = 0; up = 0; down = 0;
    #1 clk = 1; reset = 0; up = 0; down = 0;
    #1 clk = 0; reset = 0; up = 0; down = 0;
    #1 clk = 1; reset = 0; up = 1; down = 0;
    #1 clk = 0; reset = 0; up = 0; down = 0;
    #1 clk = 1; reset = 0; up = 0; down = 0;
    #1 clk = 0; reset = 0; up = 0; down = 0;
    #1 clk = 1; reset = 0; up = 0; down = 0;
    #1 clk = 0; reset = 0; up = 0; down = 0;
    #1 clk = 1; reset = 0; up = 0; down = 0;
    #1 clk = 0; reset = 0; up = 0; down = 0;
    #1 clk = 1; reset = 0; up = 0; down = 0;
    #1 clk = 0; reset = 0; up = 0; down = 0;
    #1 clk = 1; reset = 0; up = 0; down = 0;
    #1 clk = 0; reset = 0; up = 0; down = 0;
    #1 clk = 1; reset = 0; up = 0; down = 0;
    #1 clk = 0; reset = 0; up = 0; down = 0;
    #1 clk = 1; reset = 0; up = 0; down = 0;
    #1 clk = 0; reset = 0; up = 0; down = 0;
    #1 clk = 1; reset = 0; up = 0; down = 0;
    #1 clk = 0; reset = 0; up = 0; down = 0;
    #1 clk = 1; reset = 0; up = 0; down = 0;
    #1 clk = 0; reset = 0; up = 0; down = 0;
    #1 clk = 1; reset = 0; up = 0; down = 0;
    #1 clk = 0; reset = 0; up = 0; down = 0;
    #1 clk = 1; reset = 0; up = 0; down = 0;
    #1 clk = 0; reset = 0; up = 0; down = 0;
    #1 clk = 1; reset = 0; up = 0; down = 0;
    #1 clk = 0; reset = 0; up = 0; down = 0;
    #1 clk = 1; reset = 0; up = 0; down = 0;
    #1 clk = 0; reset = 0; up = 0; down = 0;
    #1 clk = 1; reset = 0; up = 0; down = 0;
    #1 clk = 0; reset = 0; up = 0; down = 0;



    $finish;
end

initial begin
$dumpfile("ala.vcd"); 
$dumpvars;
end

endmodule

trash/ala.vcd
$date
	Wed May 24 21:28:12 2023
$end
$version
	Icarus Verilog
$end
$timescale
	1s
$end
$scope module test_bench $end
$var wire 7 ! number [6:0] $end
$var reg 1 " clk $end
$var reg 1 # down $end
$var reg 1 $ reset $end
$var reg 1 % up $end
$scope module instancia $end
$var wire 1 " clk $end
$var wire 1 # down $end
$var wire 1 $ reset $end
$var wire 7 & salida [6:0] $end
$var wire 1 % up $end
$var reg 3 ' current_state [2:0] $end
$var reg 3 ( next_state [2:0] $end
$var reg 7 ) number [6:0] $end
$upscope $end
$upscope $end
$enddefinitions $end
#0
$dumpvars
bx )
b0 (
b0 '
bx &
0%
1$
0#
0"
bx !
$end
#1
b0 !
b0 &
b0 )
1"
#2
0$
0"
#3
1"
#4
0"
#5
b1 (
1%
1"
#6
0%
0"
#7
b10 (
b1 '
1"
#8
0"
#9
b101 (
b1 !
b1 &
b1 )
b10 '
1"
#10
0"
#11
b10 (
b10 !
b10 &
b10 )
b101 '
1"
#12
0"
#13
b101 (
b11 !
b11 &
b11 )
b10 '
1"
#14
0"
#15
b10 (
b100 !
b100 &
b100 )
b101 '
1"
#16
0"
#17
b101 (
b101 !
b101 &
b101 )
b10 '
1"
#18
0"
#19
b10 (
b110 !
b110 &
b110 )
b101 '
1"
#20
0"
#21
b101 (
b111 !
b111 &
b111 )
b10 '
1"
#22
0"
#23
b10 (
b1000 !
b1000 &
b1000 )
b101 '
1"
#24
0"
#25
b101 (
b1001 !
b1001 &
b1001 )
b10 '
1"
#26
0"
#27
b10 (
b1010 !
b1010 &
b1010 )
b101 '
1"
#28
0"
#29
b101 (
b1011 !
b1011 &
b1011 )
b10 '
1"
#30
0"
#31
b10 (
b1100 !
b1100 &
b1100 )
b101 '
1"
#32
0"
#33
b101 (
b1101 !
b1101 &
b1101 )
b10 '
1"
#34
0"
#35
b10 (
b1110 !
b1110 &
b1110 )
b101 '
1"
#36
0"
#37
b101 (
b1111 !
b1111 &
b1111 )
b10 '
1"
#38
0"
#39
b10 (
b10000 !
b10000 &
b10000 )
b101 '
1"
#40
0"
#41
b101 (
b10001 !
b10001 &
b10001 )
b10 '
1"
#42
0"
#43
b10 (
b10010 !
b10010 &
b10010 )
b101 '
1"
#44
0"
#45
b101 (
b10011 !
b10011 &
b10011 )
b10 '
1"
#46
0"
#47
b10 (
b10100 !
b10100 &
b10100 )
b101 '
1"
#48
0"
#49
b101 (
b10101 !
b10101 &
b10101 )
b10 '
1"
#50
0"
#51
b10 (
b10110 !
b10110 &
b10110 )
b101 '
1"
#52
0"
#53
b101 (
b10111 !
b10111 &
b10111 )
b10 '
1"
#54
0"
#55
b10 (
b11000 !
b11000 &
b11000 )
b101 '
1"
#56
0"
#57
b101 (
b11001 !
b11001 &
b11001 )
b10 '
1"
#58
0"
#59
b10 (
b11010 !
b11010 &
b11010 )
b101 '
1"
#60
0"
#61
b101 (
b11011 !
b11011 &
b11011 )
b10 '
1"
#62
0"
#63
b10 (
b11100 !
b11100 &
b11100 )
b101 '
1"
#64
0"
#65
b101 (
b11101 !
b11101 &
b11101 )
b10 '
1"
#66
0"
#67
b10 (
b11110 !
b11110 &
b11110 )
b101 '
1"
#68
0"
#69
b101 (
b11111 !
b11111 &
b11111 )
b10 '
1"
#70
0"
#71
b10 (
b100000 !
b100000 &
b100000 )
b101 '
1"
#72
0"
#73
b101 (
b100001 !
b100001 &
b100001 )
b10 '
1"
#74
0"
#75
b10 (
b100010 !
b100010 &
b100010 )
b101 '
1"
#76
0"
#77
b101 (
b100011 !
b100011 &
b100011 )
b10 '
1"
#78
0"
#79
b10 (
b100100 !
b100100 &
b100100 )
b101 '
1"
#80
0"
#81
b101 (
b100101 !
b100101 &
b100101 )
b10 '
1"
#82
0"
#83
b10 (
b100110 !
b100110 &
b100110 )
b101 '
1"
#84
0"
#85
b101 (
b100111 !
b100111 &
b100111 )
b10 '
1"
#86
0"
#87
b10 (
b101000 !
b101000 &
b101000 )
b101 '
1"
#88
0"
#89
b101 (
b101001 !
b101001 &
b101001 )
b10 '
1"
#90
0"
#91
b10 (
b101010 !
b101010 &
b101010 )
b101 '
1"
#92
0"
#93
b101 (
b101011 !
b101011 &
b101011 )
b10 '
1"
#94
0"
#95
b10 (
b101100 !
b101100 &
b101100 )
b101 '
1"
#96
0"
#97
b101 (
b101101 !
b101101 &
b101101 )
b10 '
1"
#98
0"
#99
b10 (
b101110 !
b101110 &
b101110 )
b101 '
1"
#100
0"
#101
b101 (
b101111 !
b101111 &
b101111 )
b10 '
1"
#102
0"
#103
b10 (
b110000 !
b110000 &
b110000 )
b101 '
1"
#104
0"
#105
b101 (
b110001 !
b110001 &
b110001 )
b10 '
1"
#106
0"
#107
b10 (
b110010 !
b110010 &
b110010 )
b101 '
1"
#108
0"
#109
b101 (
b110011 !
b110011 &
b110011 )
b10 '
1"
#110
0"
#111
b10 (
b110100 !
b110100 &
b110100 )
b101 '
1"
#112
0"
#113
b101 (
b110101 !
b110101 &
b110101 )
b10 '
1"
#114
0"
#115
b10 (
b110110 !
b110110 &
b110110 )
b101 '
1"
#116
0"
#117
b101 (
b110111 !
b110111 &
b110111 )
b10 '
1"
#118
0"
#119
b10 (
b111000 !
b111000 &
b111000 )
b101 '
1"
#120
0"
#121
b101 (
b111001 !
b111001 &
b111001 )
b10 '
1"
#122
0"
#123
b10 (
b111010 !
b111010 &
b111010 )
b101 '
1"
#124
0"
#125
b101 (
b111011 !
b111011 &
b111011 )
b10 '
1"
#126
0"
#127
b10 (
b111100 !
b111100 &
b111100 )
b101 '
1"
#128
0"
#129
b101 (
b111101 !
b111101 &
b111101 )
b10 '
1"
#130
0"
#131
b10 (
b111110 !
b111110 &
b111110 )
b101 '
1"
#132
0"
#133
b101 (
b111111 !
b111111 &
b111111 )
b10 '
1"
#134
0"
#135
b10 (
b1000000 !
b1000000 &
b1000000 )
b101 '
1"
#136
0"
#137
b101 (
b1000001 !
b1000001 &
b1000001 )
b10 '
1"
#138
0"
#139
b10 (
b1000010 !
b1000010 &
b1000010 )
b101 '
1"
#140
0"
#141
b101 (
b1000011 !
b1000011 &
b1000011 )
b10 '
1"
#142
0"
#143
b10 (
b1000100 !
b1000100 &
b1000100 )
b101 '
1"
#144
0"
#145
b101 (
b1000101 !
b1000101 &
b1000101 )
b10 '
1"
#146
0"
#147
b10 (
b1000110 !
b1000110 &
b1000110 )
b101 '
1"
#148
0"
#149
b101 (
b1000111 !
b1000111 &
b1000111 )
b10 '
1"
#150
0"
#151
b10 (
b1001000 !
b1001000 &
b1001000 )
b101 '
1"
#152
0"
#153
b101 (
b1001001 !
b1001001 &
b1001001 )
b10 '
1"
#154
0"
#155
b10 (
b1001010 !
b1001010 &
b1001010 )
b101 '
1"
#156
0"
#157
b101 (
b1001011 !
b1001011 &
b1001011 )
b10 '
1"
#158
0"
#159
b10 (
b1001100 !
b1001100 &
b1001100 )
b101 '
1"
#160
0"
#161
b101 (
b1001101 !
b1001101 &
b1001101 )
b10 '
1"
#162
0"
#163
b10 (
b1001110 !
b1001110 &
b1001110 )
b101 '
1"
#164
0"
#165
b101 (
b1001111 !
b1001111 &
b1001111 )
b10 '
1"
#166
0"
#167
b10 (
b1010000 !
b1010000 &
b1010000 )
b101 '
1"
#168
0"
#169
b101 (
b1010001 !
b1010001 &
b1010001 )
b10 '
1"
#170
0"
#171
b10 (
b1010010 !
b1010010 &
b1010010 )
b101 '
1"
#172
0"
#173
b101 (
b1010011 !
b1010011 &
b1010011 )
b10 '
1"
#174
0"
#175
b10 (
b1010100 !
b1010100 &
b1010100 )
b101 '
1"
#176
0"
#177
b101 (
b1010101 !
b1010101 &
b1010101 )
b10 '
1"
#178
0"
#179
b10 (
b1010110 !
b1010110 &
b1010110 )
b101 '
1"
#180
0"
#181
b101 (
b1010111 !
b1010111 &
b1010111 )
b10 '
1"
#182
0"
#183
b10 (
b1011000 !
b1011000 &
b1011000 )
b101 '
1"
#184
0"
#185
b10 '
b1 (
1%
1"
#186
b101 (
0%
0"
#187
b10 (
b1011001 !
b1011001 &
b1011001 )
b101 '
1"
#188
0"
#189
b101 (
b1011010 !
b1011010 &
b1011010 )
b10 '
1"
#190
0"
#191
b10 (
b1011011 !
b1011011 &
b1011011 )
b101 '
1"
#192
0"
#193
b101 (
b1011100 !
b1011100 &
b1011100 )
b10 '
1"
#194
0"
#195
b10 (
b1011101 !
b1011101 &
b1011101 )
b101 '
1"
#196
0"
#197
b101 (
b1011110 !
b1011110 &
b1011110 )
b10 '
1"
#198
0"
#199
b10 (
b1011111 !
b1011111 &
b1011111 )
b101 '
1"
#200
0"
#201
b101 (
b1100000 !
b1100000 &
b1100000 )
b10 '
1"
#202
0"
#203
b10 (
b1100001 !
b1100001 &
b1100001 )
b101 '
1"
#204
0"
#205
b101 (
b1100010 !
b1100010 &
b1100010 )
b10 '
1"
#206
0"
#207
b10 (
b1100011 !
b1100011 &
b1100011 )
b101 '
1"
#208
0"
#209
b101 (
b1100100 !
b1100100 &
b1100100 )
b10 '
1"
#210
0"
#211
b10 (
b0 !
b0 &
b0 )
b101 '
1"
#212
0"
#213
b101 (
b1 !
b1 &
b1 )
b10 '
1"
