pruebas/lab1/p1.v
module mux_2to1(y,a,b,selector);
input a;
input b;
input selector;
output y;

wire w1;
wire w2;
wire w3;
not inverted_selector(w1,selector);

and first_and(w2,a,w1);
and second_and(w3,b,selector);
or final(y,w2,w3);

endmodule

pruebas/lab1/tb_p1.v
module tb_mux_2to1;
reg a;
reg b;
reg c; //selector
wire y;
mux_2to1 mux(y,a,b,c);
initial begin
    a = 0; b = 0; c = 0;
    #1
    a = 0; b = 0; c = 1;
    #1
    a = 0; b = 1; c = 0;
    #1
    a = 0; b = 1; c = 1;
    #1
    a = 1; b = 0; c = 0;
    #1
    a = 1; b = 0; c = 1;
    #1
    a = 1; b = 1; c = 0;
    #1
    a = 1; b = 1; c = 1;
    #1
    $finish;
end
initial begin
    $monitor("%2d:\ta = %b\t b = %b \t selector = %b\t y = %b\n",$time,a,b,c,y);
end
initial begin
    $dumpfile("p1.vcd");
    $dumpvars;
end
endmodule

pruebas/lab1/p1.vcd
$date
	Wed Apr  5 15:44:55 2023
$end
$version
	Icarus Verilog
$end
$timescale
	1s
$end
$scope module tb_mux_2to1 $end
$var wire 1 ! y $end
$var reg 1 " a $end
$var reg 1 # b $end
$var reg 1 $ c $end
$scope module mux $end
$var wire 1 " a $end
$var wire 1 # b $end
$var wire 1 $ selector $end
$var wire 1 % w1 $end
$var wire 1 & w2 $end
$var wire 1 ' w3 $end
$var wire 1 ! y $end
$upscope $end
$upscope $end
$enddefinitions $end
#0
$dumpvars
0'
0&
1%
0$
0#
0"
0!
$end
#1
0%
1$
#2
1%
0$
1#
#3
1!
0%
1'
1$
#4
1&
1!
1%
0'
0$
0#
1"
#5
0!
0&
0%
1$
#6
1!
1&
1%
0$
1#
#7
0&
0%
1'
1$
