pruebas/lab1/p2.v
module mux_2to1_b(y,a,b,c);
input a;
input b;
input c;
output y;
assign y = (a&~c) | (b&c);
endmodule

pruebas/lab1/tb_p2.v
module tb_2_mux_2to1;
reg a;
reg b;
reg c; //selector
wire y;
mux_2to1_b mux(y,a,b,c);
initial begin
    a = 0; b = 0; c = 0;
    #1
    a = 0; b = 0; c = 1;
    #1
    a = 0; b = 1; c = 0;
    #1
    a = 0; b = 1; c = 1;
    #1
    a = 1; b = 0; c = 0;
    #1
    a = 1; b = 0; c = 1;
    #1
    a = 1; b = 1; c = 0;
    #1
    a = 1; b = 1; c = 1;
    #1
    $finish;
end
initial begin
    $monitor("%2d:\ta = %b\t b = %b \t selector = %b\t y = %b\n",$time,a,b,c,y);
end
initial begin
    $dumpfile("p2.vcd");
    $dumpvars;
end
endmodule

pruebas/lab1/p2.vcd
$date
	Wed Apr  5 15:44:37 2023
$end
$version
	Icarus Verilog
$end
$timescale
	1s
$end
$scope module tb_2_mux_2to1 $end
$var wire 1 ! y $end
$var reg 1 " a $end
$var reg 1 # b $end
$var reg 1 $ c $end
$scope module mux $end
$var wire 1 " a $end
$var wire 1 # b $end
$var wire 1 $ c $end
$var wire 1 ! y $end
$upscope $end
$upscope $end
$enddefinitions $end
#0
$dumpvars
0$
0#
0"
0!
$end
#1
1$
#2
0$
1#
#3
1!
1$
#4
1!
0$
0#
1"
#5
0!
1$
#6
1!
0$
1#
#7
1$
